skew/__init__.py
skew/_version
skew/awsclient.py
skew/config.py
skew/exception.py
skew/arn/__init__.py
skew/resources/__init__.py
skew/resources/resource.py
skew/resources/aws/__init__.py
skew/resources/aws/acm.py
skew/resources/aws/apigateway.py
skew/resources/aws/autoscaling.py
skew/resources/aws/cloudformation.py
skew/resources/aws/cloudfront.py
skew/resources/aws/cloudtrail.py
skew/resources/aws/cloudwatch.py
skew/resources/aws/dynamodb.py
skew/resources/aws/ec2.py
skew/resources/aws/elasticache.py
skew/resources/aws/elasticbeanstalk.py
skew/resources/aws/elb.py
skew/resources/aws/es.py
skew/resources/aws/firehose.py
skew/resources/aws/iam.py
skew/resources/aws/kinesis.py
skew/resources/aws/lambda.py
skew/resources/aws/rds.py
skew/resources/aws/redshift.py
skew/resources/aws/route53.py
skew/resources/aws/s3.py
skew/resources/aws/sns.py
skew/resources/aws/sqs.py
skew-0.19.0.dist-info/LICENSE
skew-0.19.0.dist-info/METADATA
skew-0.19.0.dist-info/WHEEL
skew-0.19.0.dist-info/top_level.txt
skew-0.19.0.dist-info/RECORD
