Metadata-Version: 2.1
Name: skew
Version: 0.19.0
Summary: A flat address space for all your AWS resources.
Home-page: https://github.com/scopely-devops/skew
Author: Mitch Garnaat
Author-email: mitch@garnaat.com
License: Apache License 2.0
Platform: UNKNOWN
Classifier: Development Status :: 4 - Beta
Classifier: Intended Audience :: Developers
Classifier: Intended Audience :: System Administrators
Classifier: Natural Language :: English
Classifier: License :: OSI Approved :: Apache Software License
Classifier: Programming Language :: Python :: 2
Classifier: Programming Language :: Python :: 3
Requires-Dist: boto3 (>=1.2.3)
Requires-Dist: six (>=1.9.0)
Requires-Dist: python-dateutil (<3.0.0,>=2.1)
Requires-Dist: PyYAML (>=3.11)
